{
  "version": "1.4",
  "timestamp": "2025-05-08T04:14:43.955909",
  "description": "Iteration on v1.3 model for C-class flares with 24h window",
  "flare_class": "C",
  "time_window": "24",
  "hyperparameters": {
    "learning_rate": 0.0001,
    "batch_size": 512,
    "early_stopping_patience": 5,
    "epochs": 100,
    "num_transformer_blocks": 6,
    "embed_dim": 128,
    "num_heads": 4,
    "ff_dim": 256,
    "dropout_rate": 0.2,
    "focal_loss": true,
    "focal_loss_alpha": 0.25,
    "focal_loss_gamma": 2.0,
    "class_weights": {
      "0": 1.0,
      "1": 0.4421536237869089
    },
    "previous_version": "1.3"
  },
  "performance": {
    "final_training_accuracy": 0.9711163640022278,
    "final_training_loss": 0.016338596120476723,
    "epochs_trained": 100,
    "final_training_tss": 0.9459660053253174
  },
  "git_info": {
    "commit": "32c7c105f16dc2fd8b8baadb45060d62cbd8acc8",
    "branch": "pytorch-rewrite"
  },
  "architecture": {
    "name": "SolarKnowledge",
    "input_shape": [
      10,
      9
    ],
    "num_params": 1999746,
    "precision": "<Policy \"mixed_float16\">"
  }
}